nox_uv/__init__.py
nox_uv/py.typed
nox_uv-0.6.3.dist-info/licenses/LICENSE.txt
nox_uv-0.6.3.dist-info/WHEEL
nox_uv-0.6.3.dist-info/METADATA
nox_uv-0.6.3.dist-info/RECORD
