Metadata-Version: 2.4
Name: nox-uv
Version: 0.6.3
Summary: Facilitate nox integration with uv for Python projects
Keywords: nox,uv
Author: Dan Tebben
Author-email: Dan Tebben <dantebben@gmail.com>
License-Expression: MIT
License-File: LICENSE.txt
Classifier: Development Status :: 4 - Beta
Classifier: Intended Audience :: Developers
Classifier: License :: OSI Approved :: MIT License
Classifier: Operating System :: OS Independent
Classifier: Programming Language :: Python
Classifier: Programming Language :: Python :: 3
Classifier: Programming Language :: Python :: 3.9
Classifier: Programming Language :: Python :: 3.10
Classifier: Programming Language :: Python :: 3.11
Classifier: Programming Language :: Python :: 3.12
Classifier: Programming Language :: Python :: 3.13
Classifier: Programming Language :: Python :: 3.14
Classifier: Topic :: Software Development :: Testing
Classifier: Typing :: Typed
Requires-Dist: nox>=2025.5.1
Requires-Python: >=3.9
Project-URL: Homepage, https://github.com/dantebben/nox-uv
Project-URL: Issues, https://github.com/dantebben/nox-uv/issues
Project-URL: Repository, https://github.com/dantebben/nox-uv
